e2b_agent/__init__.py
e2b_agent/agent.py
e2b_agent/dependencies.py
e2b_agent/models.py
e2b_agent/server.py
e2b_agent_protocol-0.0.1.dist-info/METADATA
e2b_agent_protocol-0.0.1.dist-info/WHEEL
e2b_agent_protocol-0.0.1.dist-info/entry_points.txt
e2b_agent_protocol-0.0.1.dist-info/RECORD
